email_verification_task_foragerai/__init__.py
email_verification_task_foragerai/api/__init__.py
email_verification_task_foragerai/api/check_emails/__init__.py
email_verification_task_foragerai/api/check_emails/routes.py
email_verification_task_foragerai/api/crud/__init__.py
email_verification_task_foragerai/api/crud/routes.py
email_verification_task_foragerai/api/healthcheck/__init__.py
email_verification_task_foragerai/api/healthcheck/routes.py
email_verification_task_foragerai/api/routers.py
email_verification_task_foragerai/core/__init__.py
email_verification_task_foragerai/core/config.py
email_verification_task_foragerai/crud/__init__.py
email_verification_task_foragerai/crud/base.py
email_verification_task_foragerai/crud/email_results.py
email_verification_task_foragerai/schemas/__init__.py
email_verification_task_foragerai/schemas/email.py
email_verification_task_foragerai/services/__init__.py
email_verification_task_foragerai/services/email_manager.py
email_verification_task_foragerai/utils/__init__.py
email_verification_task_foragerai/utils/storage.py
email_verification_task_foragerai-0.1.1.dist-info/METADATA
email_verification_task_foragerai-0.1.1.dist-info/WHEEL
email_verification_task_foragerai-0.1.1.dist-info/RECORD
