Metadata-Version: 2.1
Name: email_verification_task_ForagerAI
Version: 0.1.1
Summary: A FastAPI project for email verification.
License: MIT
Author: Oleksii R
Author-email: 88157588+alexsproject@users.noreply.github.com
Requires-Python: >=3.11,<4.0
Classifier: License :: OSI Approved :: MIT License
Classifier: Programming Language :: Python :: 3
Classifier: Programming Language :: Python :: 3.11
Classifier: Programming Language :: Python :: 3.12
Requires-Dist: fastapi (>=0.108.0,<0.109.0)
Requires-Dist: httpx (>=0.26.0,<0.27.0)
Requires-Dist: pydantic-settings (>=2.1.0,<3.0.0)
Requires-Dist: pydantic[email] (>=2.5.3,<3.0.0)
Requires-Dist: uvicorn (>=0.25.0,<0.26.0)
